eclipseprofileselector/__init__.py
eclipseprofileselector/profile.py
eclipseprofileselector/ui.glade
eclipseprofileselector-0.2.2.dist-info/entry_points.txt
eclipseprofileselector-0.2.2.dist-info/metadata.json
eclipseprofileselector-0.2.2.dist-info/DESCRIPTION.rst
eclipseprofileselector-0.2.2.dist-info/top_level.txt
eclipseprofileselector-0.2.2.dist-info/RECORD
eclipseprofileselector-0.2.2.dist-info/WHEEL
eclipseprofileselector-0.2.2.dist-info/zip-safe
eclipseprofileselector-0.2.2.dist-info/METADATA
