Metadata-Version: 2.0
Name: eclipseprofileselector
Version: 0.2.2
Summary: Manage separate Eclipse profiles and workspaces with a nice graphical user interface.
Home-page: https://github.com/privatwolke/eclipseprofileselector
Author: Stephan Klein
Author-email: UNKNOWN
License: MIT
Keywords: eclipse profile
Platform: UNKNOWN
Classifier: Development Status :: 4 - Beta
Classifier: Environment :: X11 Applications :: GTK
Classifier: Intended Audience :: Developers
Classifier: License :: OSI Approved :: MIT License
Classifier: Natural Language :: English
Classifier: Operating System :: POSIX
Classifier: Programming Language :: Python :: 2.7
Classifier: Programming Language :: Python :: 3
Classifier: Topic :: Utilities
